CONTRIBUTING.md
MANIFEST.in
README.rst
setup.py
docs/HISTORY.txt
docs/LICENSE.GPL
docs/LICENSE.txt
eea/__init__.py
eea.async.manager.egg-info/PKG-INFO
eea.async.manager.egg-info/SOURCES.txt
eea.async.manager.egg-info/dependency_links.txt
eea.async.manager.egg-info/entry_points.txt
eea.async.manager.egg-info/namespace_packages.txt
eea.async.manager.egg-info/not-zip-safe
eea.async.manager.egg-info/requires.txt
eea.async.manager.egg-info/top_level.txt
eea/async/__init__.py
eea/async/manager/README.txt
eea/async/manager/__init__.py
eea/async/manager/config.py
eea/async/manager/configure.zcml
eea/async/manager/interfaces.py
eea/async/manager/permissions.zcml
eea/async/manager/profiles.zcml
eea/async/manager/setuphandlers.py
eea/async/manager/version.txt
eea/async/manager/browser/__init__.py
eea/async/manager/browser/configure.zcml
eea/async/manager/browser/app/__init__.py
eea/async/manager/browser/app/dispatchers.py
eea/async/manager/browser/app/jobs.py
eea/async/manager/browser/app/queues.py
eea/async/manager/browser/app/quotas.py
eea/async/manager/browser/app/recover.py
eea/async/manager/browser/js/controlpanel.js
eea/async/manager/browser/zpt/dispatchers.pt
eea/async/manager/browser/zpt/jobs.pt
eea/async/manager/browser/zpt/queues.pt
eea/async/manager/browser/zpt/quotas.pt
eea/async/manager/browser/zpt/recover.pt
eea/async/manager/locales/eea.pot
eea/async/manager/locales/update.sh
eea/async/manager/profiles/default/browserlayer.xml
eea/async/manager/profiles/default/controlpanel.xml
eea/async/manager/profiles/default/metadata.xml
eea/async/manager/profiles/default/rolemap.xml
eea/async/manager/profiles/uninstall/browserlayer.xml
eea/async/manager/tests/__init__.py
eea/async/manager/tests/base.py
eea/async/manager/tests/test_doctests.py
eea/async/manager/upgrades/__init__.py
eea/async/manager/upgrades/configure.zcml